setup.py
graphite_anomaly_detector/__init__.py
graphite_anomaly_detector/generate_report.py
graphite_anomaly_detector/test_local.py
graphite_anomaly_detector/view_log.py
graphite_anomaly_detector.egg-info/PKG-INFO
graphite_anomaly_detector.egg-info/SOURCES.txt
graphite_anomaly_detector.egg-info/dependency_links.txt
graphite_anomaly_detector.egg-info/entry_points.txt
graphite_anomaly_detector.egg-info/requires.txt
graphite_anomaly_detector.egg-info/top_level.txt
graphite_anomaly_detector/detector/__init__.py
graphite_anomaly_detector/detector/detector.py
graphite_anomaly_detector/detector/saxpy.py
graphite_anomaly_detector/detector/spike_detector.py