Metadata-Version: 1.1
Name: graphite-anomaly-detector
Version: 0.2.1
Summary: Tool for detecting spikes in Graphite timeseries
Home-page: https://github.com/mihaibivol/Graphite-Anomaly-Detector/
Author: Mihai Bivol
Author-email: mm.bivol@gmail.com
License: UNKNOWN
Download-URL: https://github.com/mihaibivol/Graphite-Anomaly-Detector/
Platform: any
